Metadata-Version: 1.1
Name: codehint
Version: 0.0.1
Summary: CodeHint is a package for describing python functions and methods in console during runtime.
Home-page: http://github.com/ipazc/codehint
Author: Iván de Paz Centeno
Author-email: ipazc@unileon.es
License: MIT
Keywords: hint functions python console runtime describe code
Platform: UNKNOWN
Classifier: Environment :: Console
Classifier: Intended Audience :: Developers
Classifier: Intended Audience :: Education
Classifier: Intended Audience :: Science/Research
Classifier: Natural Language :: English
Classifier: Programming Language :: Python :: 3.4
Classifier: Programming Language :: Python :: 3.5
Classifier: Programming Language :: Python :: 3.6
Classifier: Programming Language :: Python :: 3.7
